source/__init__.py
source/__version__.py
source/razor.py
razor_proxy-0.1.dist-info/LICENSE
razor_proxy-0.1.dist-info/METADATA
razor_proxy-0.1.dist-info/NOTICE
razor_proxy-0.1.dist-info/WHEEL
razor_proxy-0.1.dist-info/entry_points.txt
razor_proxy-0.1.dist-info/top_level.txt
razor_proxy-0.1.dist-info/RECORD
