Metadata-Version: 2.1
Name: razor-proxy
Version: 0.1
Summary: High Performance Proxy Server
Home-page: https://www.github.com/xsxo/razor-proxy
Author: xsxo
License: Apache-2.0
Project-URL: Source, https://www.github.com/xsxo/razor-proxy
Classifier: Programming Language :: Python :: 3
Classifier: Programming Language :: Python :: 3.6
Classifier: Programming Language :: Python :: 3.7
Classifier: Programming Language :: Python :: 3.8
Classifier: Programming Language :: Python :: 3.9
Classifier: Programming Language :: Python :: 3.10
Classifier: Programming Language :: Python :: 3.11
Classifier: Programming Language :: Python :: 3.12
Classifier: Operating System :: OS Independent
Classifier: License :: OSI Approved :: Apache Software License
Classifier: Programming Language :: Python :: Implementation :: CPython
Classifier: Programming Language :: Python :: Implementation :: PyPy
License-File: LICENSE
License-File: NOTICE
